h8mail/__init__.py
h8mail/__main__.py
h8mail/utils/__init__.py
h8mail/utils/breachcompilation.py
h8mail/utils/chase.py
h8mail/utils/classes.py
h8mail/utils/colors.py
h8mail/utils/gen_config.py
h8mail/utils/helpers.py
h8mail/utils/intelx.py
h8mail/utils/intelx_helpers.py
h8mail/utils/localgzipsearch.py
h8mail/utils/localsearch.py
h8mail/utils/print_json.py
h8mail/utils/print_results.py
h8mail/utils/run.py
h8mail/utils/summary.py
h8mail/utils/url.py
h8mail/utils/version.py
h8mail-2.5.6.dist-info/DESCRIPTION.rst
h8mail-2.5.6.dist-info/METADATA
h8mail-2.5.6.dist-info/RECORD
h8mail-2.5.6.dist-info/WHEEL
h8mail-2.5.6.dist-info/entry_points.txt
h8mail-2.5.6.dist-info/metadata.json
h8mail-2.5.6.dist-info/top_level.txt
tests/__init__.py
tests/test_h8mail.py
