Metadata-Version: 1.1
Name: h8mail
Version: 2.5.6
Summary: Email OSINT and password breach hunting. Use h8mail to find passwords through different breach and reconnaissance services, or using your local data
Home-page: https://github.com/khast3x/h8mail
Author: khast3x
Author-email: k@khast3x.club
License: BSD license
Keywords: h8mail
Platform: UNKNOWN
Classifier: Development Status :: 5 - Production/Stable
Classifier: Intended Audience :: Developers
Classifier: License :: OSI Approved :: BSD License
Classifier: Natural Language :: English
Classifier: Programming Language :: Python :: 3.6
Classifier: Programming Language :: Python :: 3.7
Classifier: Environment :: Console
